<?xml version="1.0" encoding="utf-8"?><category name="Terms"><events><event source="EXCHANGE/PUBLIC/CALENDAR" last-verified="2014-01-28T09:00:03" last-modified="2013-09-02T15:26:52"><date>19/07/2013</date><title>Summer Term Ends at 14:30</title><categories><category>Event</category><category>Terms</category></categories><visibilities><visibility>Parents</visibility><visibility>Staff</visibility><visibility>Students</visibility></visibilities></event><event source="EXCHANGE/PUBLIC/CALENDAR" last-verified="2014-01-28T09:00:03" last-modified="2013-09-19T08:31:24"><date>04/09/2013</date><title>Autumn Term Starts</title><categories><category>Highlight</category><category>Terms</category></categories><visibilities><visibility>Parents</visibility><visibility>Public</visibility><visibility>Staff</visibility><visibility>Students</visibility></visibilities></event><event source="EXCHANGE/PUBLIC/CALENDAR" last-verified="2014-01-28T09:00:03" last-modified="2013-05-08T14:02:10"><date>28/10/2013</date><title>October Half-term Break</title><categories><category>Highlight</category><category>Terms</category></categories><visibilities><visibility>Parents</visibility><visibility>Public</visibility><visibility>Staff</visibility><visibility>Students</visibility></visibilities></event><event source="EXCHANGE/PUBLIC/CALENDAR" last-verified="2014-01-28T09:00:03" last-modified="2013-05-08T14:02:10"><date>29/10/2013</date><title>October Half-term Break</title><categories><category>Highlight</category><category>Terms</category></categories><visibilities><visibility>Parents</visibility><visibility>Public</visibility><visibility>Staff</visibility><visibility>Students</visibility></visibilities></event><event source="EXCHANGE/PUBLIC/CALENDAR" last-verified="2014-01-28T09:00:03" last-modified="2013-05-08T14:02:10"><date>30/10/2013</date><title>October Half-term Break</title><categories><category>Highlight</category><category>Terms</category></categories><visibilities><visibility>Parents</visibility><visibility>Public</visibility><visibility>Staff</visibility><visibility>Students</visibility></visibilities></event><event source="EXCHANGE/PUBLIC/CALENDAR" last-verified="2014-01-28T09:00:03" last-modified="2013-05-08T14:02:10"><date>31/10/2013</date><title>October Half-term Break</title><categories><category>Highlight</category><category>Terms</category></categories><visibilities><visibility>Parents</visibility><visibility>Public</visibility><visibility>Staff</visibility><visibility>Students</visibility></visibilities></event><event source="EXCHANGE/PUBLIC/CALENDAR" last-verified="2014-01-28T09:00:03" last-modified="2013-05-08T14:02:10"><date>01/11/2013</date><title>October Half-term Break</title><categories><category>Highlight</category><category>Terms</category></categories><visibilities><visibility>Parents</visibility><visibility>Public</visibility><visibility>Staff</visibility><visibility>Students</visibility></visibilities></event><event source="EXCHANGE/PUBLIC/CALENDAR" last-verified="2014-01-28T09:00:03" last-modified="2013-05-08T13:56:17"><date>19/12/2013</date><title>Autumn Term Ends at 14:30</title><categories><category>Highlight</category><category>Terms</category></categories><visibilities><visibility>Parents</visibility><visibility>Public</visibility><visibility>Staff</visibility><visibility>Students</visibility></visibilities></event><event source="EXCHANGE/PUBLIC/CALENDAR" last-verified="2014-01-28T09:00:03" last-modified="2013-05-08T13:52:58"><date>07/01/2014</date><title>Spring Term Starts</title><categories><category>Highlight</category><category>Terms</category></categories><visibilities><visibility>Parents</visibility><visibility>Public</visibility><visibility>Staff</visibility><visibility>Students</visibility></visibilities></event><event source="EXCHANGE/PUBLIC/CALENDAR" last-verified="2014-01-28T09:00:03" last-modified="2013-05-08T14:03:28"><date>17/02/2014</date><title>February Half-Term Break</title><categories><category>Highlight</category><category>Terms</category></categories><visibilities><visibility>Parents</visibility><visibility>Public</visibility><visibility>Staff</visibility><visibility>Students</visibility></visibilities></event><event source="EXCHANGE/PUBLIC/CALENDAR" last-verified="2014-01-28T09:00:03" last-modified="2013-05-08T14:03:28"><date>18/02/2014</date><title>February Half-Term Break</title><categories><category>Highlight</category><category>Terms</category></categories><visibilities><visibility>Parents</visibility><visibility>Public</visibility><visibility>Staff</visibility><visibility>Students</visibility></visibilities></event><event source="EXCHANGE/PUBLIC/CALENDAR" last-verified="2014-01-28T09:00:03" last-modified="2013-05-08T14:03:28"><date>19/02/2014</date><title>February Half-Term Break</title><categories><category>Highlight</category><category>Terms</category></categories><visibilities><visibility>Parents</visibility><visibility>Public</visibility><visibility>Staff</visibility><visibility>Students</visibility></visibilities></event><event source="EXCHANGE/PUBLIC/CALENDAR" last-verified="2014-01-28T09:00:03" last-modified="2013-05-08T14:03:28"><date>20/02/2014</date><title>February Half-Term Break</title><categories><category>Highlight</category><category>Terms</category></categories><visibilities><visibility>Parents</visibility><visibility>Public</visibility><visibility>Staff</visibility><visibility>Students</visibility></visibilities></event><event source="EXCHANGE/PUBLIC/CALENDAR" last-verified="2014-01-28T09:00:03" last-modified="2013-05-08T14:03:28"><date>21/02/2014</date><title>February Half-Term Break</title><categories><category>Highlight</category><category>Terms</category></categories><visibilities><visibility>Parents</visibility><visibility>Public</visibility><visibility>Staff</visibility><visibility>Students</visibility></visibilities></event><event source="EXCHANGE/PUBLIC/CALENDAR" last-verified="2014-01-28T09:00:03" last-modified="2013-05-08T13:57:07"><date>04/04/2014</date><title>Spring Term Ends at 14:30</title><categories><category>Highlight</category><category>Terms</category></categories><visibilities><visibility>Parents</visibility><visibility>Public</visibility><visibility>Staff</visibility><visibility>Students</visibility></visibilities></event><event source="EXCHANGE/PUBLIC/CALENDAR" last-verified="2014-01-28T09:00:03" last-modified="2013-05-08T13:53:38"><date>23/04/2014</date><title>Summer Term Starts</title><categories><category>Highlight</category><category>Terms</category></categories><visibilities><visibility>Parents</visibility><visibility>Public</visibility><visibility>Staff</visibility><visibility>Students</visibility></visibilities></event><event source="EXCHANGE/PUBLIC/CALENDAR" last-verified="2014-01-28T09:00:03" last-modified="2013-05-08T14:05:18"><date>26/05/2014</date><title>May Half-Term Break</title><categories><category>Highlight</category><category>Terms</category></categories><visibilities><visibility>Parents</visibility><visibility>Public</visibility><visibility>Staff</visibility><visibility>Students</visibility></visibilities></event><event source="EXCHANGE/PUBLIC/CALENDAR" last-verified="2014-01-28T09:00:03" last-modified="2013-05-08T14:05:18"><date>27/05/2014</date><title>May Half-Term Break</title><categories><category>Highlight</category><category>Terms</category></categories><visibilities><visibility>Parents</visibility><visibility>Public</visibility><visibility>Staff</visibility><visibility>Students</visibility></visibilities></event><event source="EXCHANGE/PUBLIC/CALENDAR" last-verified="2014-01-28T09:00:03" last-modified="2013-05-08T14:05:18"><date>28/05/2014</date><title>May Half-Term Break</title><categories><category>Highlight</category><category>Terms</category></categories><visibilities><visibility>Parents</visibility><visibility>Public</visibility><visibility>Staff</visibility><visibility>Students</visibility></visibilities></event><event source="EXCHANGE/PUBLIC/CALENDAR" last-verified="2014-01-28T09:00:03" last-modified="2013-05-08T14:05:18"><date>29/05/2014</date><title>May Half-Term Break</title><categories><category>Highlight</category><category>Terms</category></categories><visibilities><visibility>Parents</visibility><visibility>Public</visibility><visibility>Staff</visibility><visibility>Students</visibility></visibilities></event><event source="EXCHANGE/PUBLIC/CALENDAR" last-verified="2014-01-28T09:00:03" last-modified="2013-05-08T14:05:18"><date>30/05/2014</date><title>May Half-Term Break</title><categories><category>Highlight</category><category>Terms</category></categories><visibilities><visibility>Parents</visibility><visibility>Public</visibility><visibility>Staff</visibility><visibility>Students</visibility></visibilities></event><event source="EXCHANGE/PUBLIC/CALENDAR" last-verified="2014-01-28T09:00:03" last-modified="2013-05-08T13:58:09"><date>18/07/2014</date><title>Summer Term Ends at 14:30</title><categories><category>Highlight</category><category>Terms</category></categories><visibilities><visibility>Parents</visibility><visibility>Public</visibility><visibility>Staff</visibility><visibility>Students</visibility></visibilities></event></events><summary last-verified="2014-01-28T09:15:32" last-modified="2014-01-28T09:10:43" /></category>